deliverable_model/__init__.py
deliverable_model/batch_like_dict.py
deliverable_model/converter_base.py
deliverable_model/get_metadata.py
deliverable_model/get_saved_model.py
deliverable_model/metacontent.py
deliverable_model/processor_base.py
deliverable_model/request.py
deliverable_model/response.py
deliverable_model/utils.py
deliverable_model/builder/__init__.py
deliverable_model/builder/builder_base.py
deliverable_model/builder/deliverable_model_builder.py
deliverable_model/builder/metadata/__init__.py
deliverable_model/builder/metadata/metadata_builder.py
deliverable_model/builder/model/__init__.py
deliverable_model/builder/model/model_builder.py
deliverable_model/builder/processor/__init__.py
deliverable_model/builder/processor/processor_builder.py
deliverable_model/builder/remote_model/__init__.py
deliverable_model/builder/remote_model/remote_model_builder.py
deliverable_model/builtin/__init__.py
deliverable_model/builtin/converter/__init__.py
deliverable_model/builtin/converter/identical_converters.py
deliverable_model/builtin/converter/tf_remote_converters.py
deliverable_model/builtin/converter/tf_remote_converters_estimator.py
deliverable_model/builtin/processor/__init__.py
deliverable_model/builtin/processor/biluo_decode_processor.py
deliverable_model/builtin/processor/lookup_processor.py
deliverable_model/builtin/processor/pad_processor.py
deliverable_model/builtin/processor/str_tokens_convert_processor.py
deliverable_model/serving/__init__.py
deliverable_model/serving/deliverable_model.py
deliverable_model/serving/make_endpoint_config.py
deliverable_model/serving/make_request.py
deliverable_model/serving/simple_model_inference.py
deliverable_model/serving/metadata/__init__.py
deliverable_model/serving/metadata/metadata.py
deliverable_model/serving/model/__init__.py
deliverable_model/serving/model/model.py
deliverable_model/serving/model/model_endpoint_base.py
deliverable_model/serving/model/prototype_remote_model.py
deliverable_model-0.6.3.dist-info/AUTHORS.rst
deliverable_model-0.6.3.dist-info/LICENSE
deliverable_model-0.6.3.dist-info/METADATA
deliverable_model-0.6.3.dist-info/WHEEL
deliverable_model-0.6.3.dist-info/top_level.txt
deliverable_model-0.6.3.dist-info/RECORD
