Metadata-Version: 2.1
Name: deliverable-model
Version: 0.6.3
Summary: A cross framework machine leaning format and API specific for deploying.
Home-page: https://github.com/howl-anderson/deliverable_model
Author: Xiaoquan Kong
Author-email: u1mail2me@gmail.com
License: Apache Software License 2.0
Keywords: deliverable_model
Platform: UNKNOWN
Classifier: Development Status :: 2 - Pre-Alpha
Classifier: Intended Audience :: Developers
Classifier: License :: OSI Approved :: Apache Software License
Classifier: Natural Language :: English
Classifier: Programming Language :: Python :: 2
Classifier: Programming Language :: Python :: 2.7
Classifier: Programming Language :: Python :: 3
Classifier: Programming Language :: Python :: 3.5
Classifier: Programming Language :: Python :: 3.6
Classifier: Programming Language :: Python :: 3.7
Requires-Python: >=2.7, !=3.0.*, !=3.1.*, !=3.2.*, !=3.3.*, !=3.4.*
Requires-Dist: dill
Requires-Dist: micro-toolkit
Requires-Dist: tqdm
Requires-Dist: tensorflow (<2.0.0,>=1.15.0)
Requires-Dist: seq2annotation
Requires-Dist: tensorflow-serving-api (<2.0.0,>=1.15.0)
